panchito_lib/__init__.py
panchito_lib/primes.py
panchito_lib-0.1.5.dist-info/licenses/LICENSE
panchito_lib-0.1.5.dist-info/METADATA
panchito_lib-0.1.5.dist-info/WHEEL
panchito_lib-0.1.5.dist-info/top_level.txt
panchito_lib-0.1.5.dist-info/RECORD
